renkon/__about__.py
renkon/__init__.py
renkon/__main__.py
renkon/cli.py
renkon/client.py
renkon/config.py
renkon/py.typed
renkon/server.py
renkon/core/__init__.py
renkon/core/derivation.py
renkon/core/inference.py
renkon/core/trait.py
renkon/repo/__init__.py
renkon/repo/info.py
renkon/repo/queries.py
renkon/repo/registry.py
renkon/repo/registry.sql
renkon/repo/repository.py
renkon/repo/storage.py
renkon/task/__init__.py
renkon/task/graph.py
renkon/task/result.py
renkon/task/task.py
renkon/util/__init__.py
renkon/util/common.py
renkon/util/dag.py
renkon/util/ransac.py
renkon/util/stats.py
renkon/web/__init__.py
renkon-0.0.2.dist-info/METADATA
renkon-0.0.2.dist-info/WHEEL
renkon-0.0.2.dist-info/entry_points.txt
renkon-0.0.2.dist-info/licenses/LICENSE.txt
renkon-0.0.2.dist-info/RECORD
