Metadata-Version: 2.1
Name: renkon
Version: 0.0.2
Summary: Robust likely invariant analysis over columnar data
Project-URL: Documentation, https://github.com/DylanLukes/renkon#readme
Project-URL: Issues, https://github.com/DylanLukes/renkon/issues
Project-URL: Source, https://github.com/DylanLukes/renkon
Author-email: Dylan Lukes <lukes.dylan@gmail.com>
License-Expression: BSD-3-Clause
License-File: LICENSE.txt
Classifier: Development Status :: 4 - Beta
Classifier: Programming Language :: Python
Classifier: Programming Language :: Python :: 3.11
Classifier: Programming Language :: Python :: Implementation :: CPython
Requires-Python: >=3.11
Requires-Dist: aiosql
Requires-Dist: click
Requires-Dist: dacite
Requires-Dist: loguru
Requires-Dist: polars
Requires-Dist: pyarrow
Requires-Dist: rich
Requires-Dist: toolz
